MANIFEST.in
setup.py
smartai_plugin/CODE_OF_CONDUCT.md
smartai_plugin/LICENSE
smartai_plugin/README.md
smartai_plugin/SECURITY.md
smartai_plugin/__init__.py
smartai_plugin/demo-modeless-plugin.Dockerfile
smartai_plugin/deployment.yml
smartai_plugin/dummy-plugin.Dockerfile
smartai_plugin/gunicorn_config.py
smartai_plugin/lr-plugin.Dockerfile
smartai_plugin/requirements.txt
smartai_plugin.egg-info/PKG-INFO
smartai_plugin.egg-info/SOURCES.txt
smartai_plugin.egg-info/dependency_links.txt
smartai_plugin.egg-info/requires.txt
smartai_plugin.egg-info/top_level.txt
smartai_plugin/common/__init__.py
smartai_plugin/common/plugin_model_api.py
smartai_plugin/common/plugin_service.py
smartai_plugin/common/tsanaclient.py
smartai_plugin/common/util/__init__.py
smartai_plugin/common/util/azureblob.py
smartai_plugin/common/util/azuretable.py
smartai_plugin/common/util/constant.py
smartai_plugin/common/util/context.py
smartai_plugin/common/util/csv.py
smartai_plugin/common/util/data.py
smartai_plugin/common/util/fill_type.py
smartai_plugin/common/util/gran.py
smartai_plugin/common/util/meta.py
smartai_plugin/common/util/metric.py
smartai_plugin/common/util/model.py
smartai_plugin/common/util/monitor.py
smartai_plugin/common/util/retryrequests.py
smartai_plugin/common/util/series.py
smartai_plugin/common/util/timeutil.py
smartai_plugin/sample/__init__ .py
smartai_plugin/sample/demo_modeless/__init__ .py
smartai_plugin/sample/demo_modeless/demo_service.py
smartai_plugin/sample/demo_modeless/run_server.py
smartai_plugin/sample/demo_modeless/config/service_config.yaml
smartai_plugin/sample/dummy/__init__.py
smartai_plugin/sample/dummy/dummy_plugin_service.py
smartai_plugin/sample/dummy/run_server.py
smartai_plugin/sample/dummy/config/service_config.yaml
smartai_plugin/sample/dummy/test/dummy_test.py
smartai_plugin/sample/lr/__init__.py
smartai_plugin/sample/lr/lr_plugin_service.py
smartai_plugin/sample/lr/requirements.txt
smartai_plugin/sample/lr/run_server.py
smartai_plugin/sample/lr/config/service_config.yaml
smartai_plugin/sample/lr/test/lr_test.py