Metadata-Version: 2.1
Name: smartai-plugin
Version: 0.0.45
Summary: Time series analysis plugin
Home-page: https://github.com/Azure/smartAI-plugin
Author: Chunlei Wang
Author-email: chuwan@microsoft.com
License: MIT Licence
Keywords: pip,timeseries,plugin
Platform: UNKNOWN
Classifier: Programming Language :: Python :: 3
Classifier: License :: OSI Approved :: MIT License
Classifier: Operating System :: OS Independent
Requires-Python: >=3.6
